oneup/__init__.py
oneup/cli.py
oneup/output.py
oneup/version_checks.py
oneup-0.8.0.dist-info/LICENSE
oneup-0.8.0.dist-info/METADATA
oneup-0.8.0.dist-info/WHEEL
oneup-0.8.0.dist-info/entry_points.txt
oneup-0.8.0.dist-info/RECORD
