Metadata-Version: 2.3
Name: oneup
Version: 0.8.0
Summary: A CLI tool to check for dependency updates for Python, in Python
License: AGPL-3.0-only
Keywords: python,dependency updates,pyproject,requirements,cli
Author: Andrés Ignacio Torres
Author-email: dev@aitorres.com
Requires-Python: >=3.9,<4.0
Classifier: Development Status :: 4 - Beta
Classifier: Environment :: Console
Classifier: Intended Audience :: Developers
Classifier: Intended Audience :: System Administrators
Classifier: License :: OSI Approved :: GNU Affero General Public License v3
Classifier: Operating System :: OS Independent
Classifier: Programming Language :: Python :: 3
Classifier: Programming Language :: Python :: 3.9
Classifier: Programming Language :: Python :: 3.10
Classifier: Programming Language :: Python :: 3.11
Classifier: Programming Language :: Python :: 3.12
Classifier: Programming Language :: Python :: 3.13
Classifier: Topic :: Software Development
Classifier: Topic :: Utilities
Classifier: Typing :: Typed
Requires-Dist: requests (>=2.32.3,<3.0.0)
Requires-Dist: requirements-parser (>=0.11.0,<0.12.0)
Requires-Dist: termcolor (>=1.1.0,<2.0.0)
Requires-Dist: toml (>=0.10.2,<0.11.0)
Project-URL: Bug Tracker, https://github.com/aitorres/oneup/issues
Project-URL: Repository, https://github.com/aitorres/oneup
